invar/__init__.py
invar/py.typed
invar/core/__init__.py
invar/core/contracts.py
invar/core/doc_edit.py
invar/core/doc_parser.py
invar/core/entry_points.py
invar/core/extraction.py
invar/core/feedback.py
invar/core/format_specs.py
invar/core/format_strategies.py
invar/core/formatter.py
invar/core/hypothesis_strategies.py
invar/core/inspect.py
invar/core/lambda_helpers.py
invar/core/language.py
invar/core/models.py
invar/core/must_use.py
invar/core/parser.py
invar/core/postcondition_scope.py
invar/core/property_gen.py
invar/core/purity.py
invar/core/purity_heuristics.py
invar/core/references.py
invar/core/review_trigger.py
invar/core/rule_meta.py
invar/core/rules.py
invar/core/shell_analysis.py
invar/core/shell_architecture.py
invar/core/strategies.py
invar/core/suggestions.py
invar/core/sync_helpers.py
invar/core/tautology.py
invar/core/template_helpers.py
invar/core/template_parser.py
invar/core/timeout_inference.py
invar/core/trivial_detection.py
invar/core/ts_parsers.py
invar/core/ts_sig_parser.py
invar/core/utils.py
invar/core/verification_routing.py
invar/core/patterns/__init__.py
invar/core/patterns/detector.py
invar/core/patterns/p0_exhaustive.py
invar/core/patterns/p0_literal.py
invar/core/patterns/p0_newtype.py
invar/core/patterns/p0_nonempty.py
invar/core/patterns/p0_validation.py
invar/core/patterns/registry.py
invar/core/patterns/types.py
invar/mcp/__init__.py
invar/mcp/__main__.py
invar/mcp/handlers.py
invar/mcp/server.py
invar/node_tools/.gitignore
invar/node_tools/MANIFEST
invar/node_tools/__init__.py
invar/node_tools/ts-query.js
invar/node_tools/eslint-plugin/cli.js
invar/node_tools/eslint-plugin/cli.js.map
invar/node_tools/eslint-plugin/index.js
invar/node_tools/eslint-plugin/index.js.map
invar/node_tools/fc-runner/bundle.js
invar/node_tools/fc-runner/cli.d.ts
invar/node_tools/fc-runner/cli.d.ts.map
invar/node_tools/fc-runner/cli.js
invar/node_tools/fc-runner/cli.js.map
invar/node_tools/fc-runner/index.d.ts
invar/node_tools/fc-runner/index.d.ts.map
invar_tools-1.17.1.dist-info/METADATA
invar_tools-1.17.1.dist-info/WHEEL
invar_tools-1.17.1.dist-info/entry_points.txt
invar_tools-1.17.1.dist-info/licenses/LICENSE
invar_tools-1.17.1.dist-info/licenses/LICENSE-GPL
invar_tools-1.17.1.dist-info/licenses/NOTICE
invar_tools-1.17.1.dist-info/RECORD
