Metadata-Version: 2.4
Name: invar-tools
Version: 1.17.1
Summary: AI-native software engineering tools with design-by-contract verification
Project-URL: Homepage, https://github.com/tefx/invar
Project-URL: Documentation, https://github.com/tefx/invar#readme
Project-URL: Repository, https://github.com/tefx/invar
Project-URL: Issues, https://github.com/tefx/invar/issues
Author: Invar Team
License-Expression: GPL-3.0-or-later
License-File: LICENSE
License-File: LICENSE-GPL
License-File: NOTICE
Keywords: ai,code-quality,contracts,design-by-contract,static-analysis
Classifier: Development Status :: 3 - Alpha
Classifier: Intended Audience :: Developers
Classifier: License :: OSI Approved :: GNU General Public License v3 or later (GPLv3+)
Classifier: Programming Language :: Python :: 3
Classifier: Programming Language :: Python :: 3.11
Classifier: Programming Language :: Python :: 3.12
Classifier: Topic :: Software Development :: Quality Assurance
Classifier: Typing :: Typed
Requires-Python: >=3.11
Requires-Dist: crosshair-tool>=0.0.60
Requires-Dist: hypothesis>=6.0
Requires-Dist: invar-runtime>=1.0
Requires-Dist: jedi>=0.19
Requires-Dist: jinja2>=3.0
Requires-Dist: markdown-it-py>=3.0
Requires-Dist: mcp>=1.0
Requires-Dist: pre-commit>=3.0
Requires-Dist: pydantic>=2.0
Requires-Dist: questionary>=2.0
Requires-Dist: returns>=0.20
Requires-Dist: rich>=13.0
Requires-Dist: typer>=0.9
Provides-Extra: dev
Requires-Dist: coverage[toml]>=7.0; extra == 'dev'
Requires-Dist: mypy>=1.0; extra == 'dev'
Requires-Dist: pytest-cov>=4.0; extra == 'dev'
Requires-Dist: pytest>=7.0; extra == 'dev'
Requires-Dist: ruff>=0.1; extra == 'dev'
